rohr/__init__.py
rohr-0.2.0.dist-info/WHEEL
rohr-0.2.0.dist-info/METADATA
rohr-0.2.0.dist-info/RECORD
