Metadata-Version: 2.1
Name: rohr
Version: 0.2.0
Summary: Build easy data processing pipelines in python.
License: MIT
Author-email: Paul Frische <paul@paulfrische.xyz>
Requires-Python: >=3.4
Requires-Dist: pytest
